odoo/addons/stock_vlm_mgmt/README.rst
odoo/addons/stock_vlm_mgmt/__init__.py
odoo/addons/stock_vlm_mgmt/__manifest__.py
odoo/addons/stock_vlm_mgmt/i18n/it.po
odoo/addons/stock_vlm_mgmt/i18n/sl.po
odoo/addons/stock_vlm_mgmt/i18n/stock_vlm_mgmt.pot
odoo/addons/stock_vlm_mgmt/models/__init__.py
odoo/addons/stock_vlm_mgmt/models/stock_location.py
odoo/addons/stock_vlm_mgmt/models/stock_location_vlm_tray.py
odoo/addons/stock_vlm_mgmt/models/stock_location_vlm_tray_type.py
odoo/addons/stock_vlm_mgmt/models/stock_move_line.py
odoo/addons/stock_vlm_mgmt/models/stock_picking.py
odoo/addons/stock_vlm_mgmt/models/stock_quant.py
odoo/addons/stock_vlm_mgmt/models/stock_vlm_task.py
odoo/addons/stock_vlm_mgmt/models/vlm_tray_cell_position_mixin.py
odoo/addons/stock_vlm_mgmt/readme/CONTRIBUTORS.rst
odoo/addons/stock_vlm_mgmt/readme/DESCRIPTION.rst
odoo/addons/stock_vlm_mgmt/readme/ROADMAP.rst
odoo/addons/stock_vlm_mgmt/security/ir.model.access.csv
odoo/addons/stock_vlm_mgmt/static/description/icon.png
odoo/addons/stock_vlm_mgmt/static/description/index.html
odoo/addons/stock_vlm_mgmt/static/src/js/location_tray_matrix/stock_location_tray.esm.js
odoo/addons/stock_vlm_mgmt/static/src/js/location_tray_matrix/stock_location_tray.scss
odoo/addons/stock_vlm_mgmt/static/src/js/location_tray_matrix/stock_location_tray_views.xml
odoo/addons/stock_vlm_mgmt/static/src/js/vlm_request_button/vlm_request_views.esm.js
odoo/addons/stock_vlm_mgmt/static/src/js/vlm_request_button/vlm_request_views.xml
odoo/addons/stock_vlm_mgmt/static/src/scss/stock_vlm_mgmt.scss
odoo/addons/stock_vlm_mgmt/views/stock_location_tray_type_views.xml
odoo/addons/stock_vlm_mgmt/views/stock_location_views.xml
odoo/addons/stock_vlm_mgmt/views/stock_location_vlm_tray_views.xml
odoo/addons/stock_vlm_mgmt/views/stock_picking_views.xml
odoo/addons/stock_vlm_mgmt/views/stock_quant_views.xml
odoo/addons/stock_vlm_mgmt/views/stock_quant_vlm_views.xml
odoo/addons/stock_vlm_mgmt/views/stock_vlm_task_views.xml
odoo_addon_stock_vlm_mgmt-16.0.1.0.2.1.dist-info/METADATA
odoo_addon_stock_vlm_mgmt-16.0.1.0.2.1.dist-info/WHEEL
odoo_addon_stock_vlm_mgmt-16.0.1.0.2.1.dist-info/top_level.txt
odoo_addon_stock_vlm_mgmt-16.0.1.0.2.1.dist-info/RECORD
